rdfpandas/__init__.py
rdfpandas/graph.py
rdfpandas-1.1.7.dist-info/LICENSE
rdfpandas-1.1.7.dist-info/METADATA
rdfpandas-1.1.7.dist-info/WHEEL
rdfpandas-1.1.7.dist-info/top_level.txt
rdfpandas-1.1.7.dist-info/RECORD
