Metadata-Version: 2.1
Name: rdfpandas
Version: 1.1.7
Summary: RDF support for Pandas
Home-page: https://github.com/cadmiumkitty/rdfpandas
Author: Eugene Morozov
Author-email: emorozov@gmail.com
License: MIT
License-File: LICENSE
Requires-Dist: pandas >=2.2.2
Requires-Dist: rdflib >=6.3.2
